SWAXSanalysis/__init__.py
SWAXSanalysis/class_nexus_file.py
SWAXSanalysis/create_config.py
SWAXSanalysis/data_processing.py
SWAXSanalysis/launcher.py
SWAXSanalysis/nxfile_generator.py
SWAXSanalysis/utils.py
SWAXSanalysis/Data Treatment Center/Configs/settings_EDF2NX_XEUSS_202504090957.json
SWAXSanalysis/Data Treatment Center/Configs/settings_EDF2NX_testMachine_202507281529.json
SWAXSanalysis/Data Treatment Center/Jupyter notebooks/jupyter_launcher.bat
SWAXSanalysis/Data Treatment Center/Jupyter notebooks/NoteBook/1_Change_HDF5.ipynb
SWAXSanalysis/Data Treatment Center/Jupyter notebooks/NoteBook/2_How_to_use_NexusFile.ipynb
SWAXSanalysis/Data Treatment Center/Jupyter notebooks/NoteBook/3_Advanced_processing.ipynb
SWAXSanalysis/Data Treatment Center/Jupyter notebooks/NoteBook/Example HDF5/testSample_SAXS_00001.h5
SWAXSanalysis/Images/nxformat_icon.ico
SWAXSanalysis/__pycache__/__init__.cpython-310.pyc
SWAXSanalysis/__pycache__/class_nexus_file.cpython-310.pyc
SWAXSanalysis/__pycache__/create_config.cpython-310.pyc
SWAXSanalysis/__pycache__/data_processing.cpython-310.pyc
SWAXSanalysis/__pycache__/launcher.cpython-310.pyc
SWAXSanalysis/__pycache__/nxfile_generator.cpython-310.pyc
SWAXSanalysis/__pycache__/utils.cpython-310.pyc
SWAXSanalysis/nexus_standards/structure_NXcanSAS.json
SWAXSanalysis/nexus_standards/structure_NXunits.json
swaxsanalysis-2025.5.1.0.dist-info/licenses/LICENSE
swaxsanalysis-2025.5.1.0.dist-info/METADATA
swaxsanalysis-2025.5.1.0.dist-info/WHEEL
swaxsanalysis-2025.5.1.0.dist-info/entry_points.txt
swaxsanalysis-2025.5.1.0.dist-info/top_level.txt
swaxsanalysis-2025.5.1.0.dist-info/RECORD
