Metadata-Version: 2.4
Name: SWAXSanalysis
Version: 2025.5.1.0
Summary: Package allowing the conversion and analysis of SAXS and WAXS data (EDF format) that's fresh out of the machine. This package convertis the EDF files to an HDF5 file with the NeXus standard for the x-ray community.
Author-email: Adrien Toulouse <toulouseadrienjob@gmail.com>
License-Expression: GPL-3.0
Project-URL: Homepage, https://github.com/CEA-MetroCarac/SWAXSanalysis
Keywords: EDF,HDF5,NeXus,Data analysis,X-ray,Xeuss,SAXS,WAXS,SWAXS
Classifier: Programming Language :: Python :: 3.10
Classifier: Operating System :: Microsoft :: Windows
Classifier: Environment :: Console
Requires-Python: >=3.10
License-File: LICENSE
Requires-Dist: numpy
Requires-Dist: matplotlib
Requires-Dist: h5py
Requires-Dist: fabio
Requires-Dist: memory_profiler
Dynamic: license-file
